MANIFEST.in
README.md
setup.py
jal_nba/__init__.py
jal_nba/config.json
jal_nba/exceptions.py
jal_nba/nba.py
jal_nba/nba_teams.json
jal_nba.egg-info/PKG-INFO
jal_nba.egg-info/SOURCES.txt
jal_nba.egg-info/dependency_links.txt
jal_nba.egg-info/not-zip-safe
jal_nba.egg-info/requires.txt
jal_nba.egg-info/top_level.txt