Metadata-Version: 1.0
Name: jal-nba
Version: 0.3
Summary: Retrieve info from NBA API at stats.nba.com/stats/
Home-page: http://github.com/jalgraves/jal_nba
Author: Jonny Graves
Author-email: jal@jalgraves.com
License: MIT
Platform: UNKNOWN
